{
  "text": "Robert DeSoto added a new task",
  "attachments": [
    {
      "fallback": "Plan a vacation",
      "author_name": "Owner: rdesoto",
      "title": "Plan a vacation",
      "text": "I've been working too hard, it's time for a break.",
      "actions": [
        {
          "name": "action",
          "type": "button",
          "text": "Complete this task",
          "style": "",
          "value": "complete"
        },
        {
          "name": "tags_list",
          "type": "select",
          "text": "Add a tag...",
          "data_source": "static",
          "options": [
            {
              "text": "Launch Blocking",
              "value": "launch-blocking"
            },
            {
              "text": "Enhancement",
              "value": "enhancement"
            },
            {
              "text": "Bug",
              "value": "bug"
            }
          ]
        }
      ]
    }
  ]
}